flexanomalies/__init__.py
flexanomalies/datasets/__init__.py
flexanomalies/datasets/preprocessing_utils.py
flexanomalies/pool/__init__.py
flexanomalies/pool/aggregators_cl.py
flexanomalies/pool/aggregators_favg.py
flexanomalies/pool/aggregators_pca.py
flexanomalies/pool/aggregators_stats.py
flexanomalies/pool/primitives_cluster.py
flexanomalies/pool/primitives_deepmodel.py
flexanomalies/pool/primitives_iforest.py
flexanomalies/pool/primitives_pca.py
flexanomalies/utils/__init__.py
flexanomalies/utils/autoencoder.py
flexanomalies/utils/base_model.py
flexanomalies/utils/cluster.py
flexanomalies/utils/cnn_lstm.py
flexanomalies/utils/iforest.py
flexanomalies/utils/load_data.py
flexanomalies/utils/metrics.py
flexanomalies/utils/pca_anomaly.py
flexanomalies/utils/process_scores.py
flexanomalies/utils/save_results.py
flexanomalies/utils/test_static.py
test_json/__init__.py
flexanomalies-0.0.3.dist-info/LICENSE
flexanomalies-0.0.3.dist-info/METADATA
flexanomalies-0.0.3.dist-info/WHEEL
flexanomalies-0.0.3.dist-info/top_level.txt
flexanomalies-0.0.3.dist-info/RECORD
