Metadata-Version: 2.2
Name: flexanomalies
Version: 0.0.3
Keywords: anomaly detection federated-learning flexible outlier
License-File: LICENSE
Requires-Dist: flex
Requires-Dist: numpy
Requires-Dist: tensorflow
Requires-Dist: scikit-learn
Requires-Dist: pandas
Dynamic: description
Dynamic: description-content-type
Dynamic: keywords
Dynamic: requires-dist
